{
  "options": {
    "characterLimit": 6,
    "maxLifePoint": 1,
    "initialCost": 10,
    "maxCost": 99,
    "costIncreaseTime": 1.0,
    "moveMultiplier": 0.5,
    "steeringEnabled": true,
    "isTrainingLevel": false,
    "isHardTrainingLevel": false,
    "isPredefinedCardsSelectable": false,
    "maxPlayTime": -1.0,
    "functionDisableMask": "NONE",
    "configBlackBoard": null
  },
  "levelId": null,
  "mapId": null,
  "bgmEvent": "rl5sky",
  "environmentSe": null,
  "mapData": {
    "map": [
      [
        54,
        55,
        56,
        57,
        58,
        59,
        60,
        61,
        62
      ],
      [
        45,
        46,
        47,
        48,
        49,
        50,
        51,
        52,
        53
      ],
      [
        36,
        37,
        38,
        39,
        40,
        41,
        42,
        43,
        44
      ],
      [
        27,
        28,
        29,
        30,
        31,
        32,
        33,
        34,
        35
      ],
      [
        18,
        19,
        20,
        21,
        22,
        23,
        24,
        25,
        26
      ],
      [
        9,
        10,
        11,
        12,
        13,
        14,
        15,
        16,
        17
      ],
      [
        0,
        1,
        2,
        3,
        4,
        5,
        6,
        7,
        8
      ]
    ],
    "tiles": [
      {
        "tileKey": "tile_forbidden",
        "heightType": "HIGHLAND",
        "buildableType": "NONE",
        "passableMask": "FLY_ONLY",
        "playerSideMask": "ALL",
        "blackboard": null,
        "effects": null
      },
      {
        "tileKey": "tile_forbidden",
        "heightType": "HIGHLAND",
        "buildableType": "NONE",
        "passableMask": "FLY_ONLY",
        "playerSideMask": "ALL",
        "blackboard": null,
        "effects": null
      },
      {
        "tileKey": "tile_forbidden",
        "heightType": "HIGHLAND",
        "buildableType": "NONE",
        "passableMask": "FLY_ONLY",
        "playerSideMask": "ALL",
        "blackboard": null,
        "effects": null
      },
      {
        "tileKey": "tile_forbidden",
        "heightType": "HIGHLAND",
        "buildableType": "NONE",
        "passableMask": "FLY_ONLY",
        "playerSideMask": "ALL",
        "blackboard": null,
        "effects": null
      },
      {
        "tileKey": "tile_forbidden",
        "heightType": "HIGHLAND",
        "buildableType": "NONE",
        "passableMask": "FLY_ONLY",
        "playerSideMask": "ALL",
        "blackboard": null,
        "effects": null
      },
      {
        "tileKey": "tile_forbidden",
        "heightType": "HIGHLAND",
        "buildableType": "NONE",
        "passableMask": "FLY_ONLY",
        "playerSideMask": "ALL",
        "blackboard": null,
        "effects": null
      },
      {
        "tileKey": "tile_end",
        "heightType": "LOWLAND",
        "buildableType": "NONE",
        "passableMask": "ALL",
        "playerSideMask": "ALL",
        "blackboard": null,
        "effects": null
      },
      {
        "tileKey": "tile_forbidden",
        "heightType": "HIGHLAND",
        "buildableType": "NONE",
        "passableMask": "FLY_ONLY",
        "playerSideMask": "ALL",
        "blackboard": null,
        "effects": null
      },
      {
        "tileKey": "tile_forbidden",
        "heightType": "HIGHLAND",
        "buildableType": "NONE",
        "passableMask": "FLY_ONLY",
        "playerSideMask": "ALL",
        "blackboard": null,
        "effects": null
      },
      {
        "tileKey": "tile_forbidden",
        "heightType": "HIGHLAND",
        "buildableType": "NONE",
        "passableMask": "FLY_ONLY",
        "playerSideMask": "ALL",
        "blackboard": null,
        "effects": null
      },
      {
        "tileKey": "tile_start",
        "heightType": "LOWLAND",
        "buildableType": "NONE",
        "passableMask": "ALL",
        "playerSideMask": "ALL",
        "blackboard": null,
        "effects": null
      },
      {
        "tileKey": "tile_floor",
        "heightType": "LOWLAND",
        "buildableType": "NONE",
        "passableMask": "ALL",
        "playerSideMask": "ALL",
        "blackboard": null,
        "effects": null
      },
      {
        "tileKey": "tile_telin",
        "heightType": "LOWLAND",
        "buildableType": "NONE",
        "passableMask": "ALL",
        "playerSideMask": "ALL",
        "blackboard": null,
        "effects": null
      },
      {
        "tileKey": "tile_forbidden",
        "heightType": "HIGHLAND",
        "buildableType": "NONE",
        "passableMask": "FLY_ONLY",
        "playerSideMask": "ALL",
        "blackboard": null,
        "effects": null
      },
      {
        "tileKey": "tile_wall",
        "heightType": "HIGHLAND",
        "buildableType": "RANGED",
        "passableMask": "FLY_ONLY",
        "playerSideMask": "ALL",
        "blackboard": null,
        "effects": null
      },
      {
        "tileKey": "tile_road",
        "heightType": "LOWLAND",
        "buildableType": "MELEE",
        "passableMask": "ALL",
        "playerSideMask": "ALL",
        "blackboard": null,
        "effects": null
      },
      {
        "tileKey": "tile_wall",
        "heightType": "HIGHLAND",
        "buildableType": "RANGED",
        "passableMask": "FLY_ONLY",
        "playerSideMask": "ALL",
        "blackboard": null,
        "effects": null
      },
      {
        "tileKey": "tile_forbidden",
        "heightType": "HIGHLAND",
        "buildableType": "NONE",
        "passableMask": "FLY_ONLY",
        "playerSideMask": "ALL",
        "blackboard": null,
        "effects": null
      },
      {
        "tileKey": "tile_forbidden",
        "heightType": "HIGHLAND",
        "buildableType": "NONE",
        "passableMask": "FLY_ONLY",
        "playerSideMask": "ALL",
        "blackboard": null,
        "effects": null
      },
      {
        "tileKey": "tile_forbidden",
        "heightType": "HIGHLAND",
        "buildableType": "NONE",
        "passableMask": "FLY_ONLY",
        "playerSideMask": "ALL",
        "blackboard": null,
        "effects": null
      },
      {
        "tileKey": "tile_forbidden",
        "heightType": "HIGHLAND",
        "buildableType": "NONE",
        "passableMask": "FLY_ONLY",
        "playerSideMask": "ALL",
        "blackboard": null,
        "effects": null
      },
      {
        "tileKey": "tile_forbidden",
        "heightType": "HIGHLAND",
        "buildableType": "NONE",
        "passableMask": "FLY_ONLY",
        "playerSideMask": "ALL",
        "blackboard": null,
        "effects": null
      },
      {
        "tileKey": "tile_dygmny_3",
        "heightType": "HIGHLAND",
        "buildableType": "RANGED",
        "passableMask": "FLY_ONLY",
        "playerSideMask": "ALL",
        "blackboard": null,
        "effects": null
      },
      {
        "tileKey": "tile_road",
        "heightType": "LOWLAND",
        "buildableType": "MELEE",
        "passableMask": "ALL",
        "playerSideMask": "ALL",
        "blackboard": null,
        "effects": null
      },
      {
        "tileKey": "tile_road",
        "heightType": "LOWLAND",
        "buildableType": "MELEE",
        "passableMask": "ALL",
        "playerSideMask": "ALL",
        "blackboard": null,
        "effects": null
      },
      {
        "tileKey": "tile_road",
        "heightType": "LOWLAND",
        "buildableType": "MELEE",
        "passableMask": "ALL",
        "playerSideMask": "ALL",
        "blackboard": null,
        "effects": null
      },
      {
        "tileKey": "tile_forbidden",
        "heightType": "HIGHLAND",
        "buildableType": "NONE",
        "passableMask": "FLY_ONLY",
        "playerSideMask": "ALL",
        "blackboard": null,
        "effects": null
      },
      {
        "tileKey": "tile_forbidden",
        "heightType": "HIGHLAND",
        "buildableType": "NONE",
        "passableMask": "FLY_ONLY",
        "playerSideMask": "ALL",
        "blackboard": null,
        "effects": null
      },
      {
        "tileKey": "tile_forbidden",
        "heightType": "HIGHLAND",
        "buildableType": "NONE",
        "passableMask": "FLY_ONLY",
        "playerSideMask": "ALL",
        "blackboard": null,
        "effects": null
      },
      {
        "tileKey": "tile_forbidden",
        "heightType": "HIGHLAND",
        "buildableType": "NONE",
        "passableMask": "FLY_ONLY",
        "playerSideMask": "ALL",
        "blackboard": null,
        "effects": null
      },
      {
        "tileKey": "tile_forbidden",
        "heightType": "HIGHLAND",
        "buildableType": "NONE",
        "passableMask": "FLY_ONLY",
        "playerSideMask": "ALL",
        "blackboard": null,
        "effects": null
      },
      {
        "tileKey": "tile_telout",
        "heightType": "LOWLAND",
        "buildableType": "NONE",
        "passableMask": "ALL",
        "playerSideMask": "ALL",
        "blackboard": null,
        "effects": null
      },
      {
        "tileKey": "tile_road",
        "heightType": "LOWLAND",
        "buildableType": "MELEE",
        "passableMask": "ALL",
        "playerSideMask": "ALL",
        "blackboard": null,
        "effects": null
      },
      {
        "tileKey": "tile_road",
        "heightType": "LOWLAND",
        "buildableType": "MELEE",
        "passableMask": "ALL",
        "playerSideMask": "ALL",
        "blackboard": null,
        "effects": null
      },
      {
        "tileKey": "tile_road",
        "heightType": "LOWLAND",
        "buildableType": "MELEE",
        "passableMask": "ALL",
        "playerSideMask": "ALL",
        "blackboard": null,
        "effects": null
      },
      {
        "tileKey": "tile_flystart",
        "heightType": "HIGHLAND",
        "buildableType": "NONE",
        "passableMask": "FLY_ONLY",
        "playerSideMask": "ALL",
        "blackboard": null,
        "effects": null
      },
      {
        "tileKey": "tile_forbidden",
        "heightType": "HIGHLAND",
        "buildableType": "NONE",
        "passableMask": "FLY_ONLY",
        "playerSideMask": "ALL",
        "blackboard": null,
        "effects": null
      },
      {
        "tileKey": "tile_forbidden",
        "heightType": "HIGHLAND",
        "buildableType": "NONE",
        "passableMask": "FLY_ONLY",
        "playerSideMask": "ALL",
        "blackboard": null,
        "effects": null
      },
      {
        "tileKey": "tile_forbidden",
        "heightType": "HIGHLAND",
        "buildableType": "NONE",
        "passableMask": "FLY_ONLY",
        "playerSideMask": "ALL",
        "blackboard": null,
        "effects": null
      },
      {
        "tileKey": "tile_forbidden",
        "heightType": "HIGHLAND",
        "buildableType": "NONE",
        "passableMask": "FLY_ONLY",
        "playerSideMask": "ALL",
        "blackboard": null,
        "effects": null
      },
      {
        "tileKey": "tile_dygmny_3",
        "heightType": "HIGHLAND",
        "buildableType": "RANGED",
        "passableMask": "FLY_ONLY",
        "playerSideMask": "ALL",
        "blackboard": null,
        "effects": null
      },
      {
        "tileKey": "tile_dygmny_1",
        "heightType": "LOWLAND",
        "buildableType": "MELEE",
        "passableMask": "ALL",
        "playerSideMask": "ALL",
        "blackboard": null,
        "effects": null
      },
      {
        "tileKey": "tile_dygmny_1",
        "heightType": "LOWLAND",
        "buildableType": "MELEE",
        "passableMask": "ALL",
        "playerSideMask": "ALL",
        "blackboard": null,
        "effects": null
      },
      {
        "tileKey": "tile_dygmny_1",
        "heightType": "LOWLAND",
        "buildableType": "MELEE",
        "passableMask": "ALL",
        "playerSideMask": "ALL",
        "blackboard": null,
        "effects": null
      },
      {
        "tileKey": "tile_forbidden",
        "heightType": "HIGHLAND",
        "buildableType": "NONE",
        "passableMask": "FLY_ONLY",
        "playerSideMask": "ALL",
        "blackboard": null,
        "effects": null
      },
      {
        "tileKey": "tile_telin",
        "heightType": "LOWLAND",
        "buildableType": "NONE",
        "passableMask": "ALL",
        "playerSideMask": "ALL",
        "blackboard": null,
        "effects": null
      },
      {
        "tileKey": "tile_floor",
        "heightType": "LOWLAND",
        "buildableType": "NONE",
        "passableMask": "ALL",
        "playerSideMask": "ALL",
        "blackboard": null,
        "effects": null
      },
      {
        "tileKey": "tile_forbidden",
        "heightType": "HIGHLAND",
        "buildableType": "NONE",
        "passableMask": "FLY_ONLY",
        "playerSideMask": "ALL",
        "blackboard": null,
        "effects": null
      },
      {
        "tileKey": "tile_forbidden",
        "heightType": "HIGHLAND",
        "buildableType": "NONE",
        "passableMask": "FLY_ONLY",
        "playerSideMask": "ALL",
        "blackboard": null,
        "effects": null
      },
      {
        "tileKey": "tile_fence_bound",
        "heightType": "LOWLAND",
        "buildableType": "MELEE",
        "passableMask": "FLY_ONLY",
        "playerSideMask": "ALL",
        "blackboard": null,
        "effects": null
      },
      {
        "tileKey": "tile_floor",
        "heightType": "LOWLAND",
        "buildableType": "NONE",
        "passableMask": "ALL",
        "playerSideMask": "ALL",
        "blackboard": null,
        "effects": null
      },
      {
        "tileKey": "tile_floor",
        "heightType": "LOWLAND",
        "buildableType": "NONE",
        "passableMask": "ALL",
        "playerSideMask": "ALL",
        "blackboard": null,
        "effects": null
      },
      {
        "tileKey": "tile_floor",
        "heightType": "LOWLAND",
        "buildableType": "NONE",
        "passableMask": "ALL",
        "playerSideMask": "ALL",
        "blackboard": null,
        "effects": null
      },
      {
        "tileKey": "tile_telout",
        "heightType": "LOWLAND",
        "buildableType": "NONE",
        "passableMask": "ALL",
        "playerSideMask": "ALL",
        "blackboard": null,
        "effects": null
      },
      {
        "tileKey": "tile_forbidden",
        "heightType": "HIGHLAND",
        "buildableType": "NONE",
        "passableMask": "FLY_ONLY",
        "playerSideMask": "ALL",
        "blackboard": null,
        "effects": null
      },
      {
        "tileKey": "tile_forbidden",
        "heightType": "HIGHLAND",
        "buildableType": "NONE",
        "passableMask": "FLY_ONLY",
        "playerSideMask": "ALL",
        "blackboard": null,
        "effects": null
      },
      {
        "tileKey": "tile_forbidden",
        "heightType": "HIGHLAND",
        "buildableType": "NONE",
        "passableMask": "FLY_ONLY",
        "playerSideMask": "ALL",
        "blackboard": null,
        "effects": null
      },
      {
        "tileKey": "tile_forbidden",
        "heightType": "HIGHLAND",
        "buildableType": "NONE",
        "passableMask": "FLY_ONLY",
        "playerSideMask": "ALL",
        "blackboard": null,
        "effects": null
      },
      {
        "tileKey": "tile_forbidden",
        "heightType": "HIGHLAND",
        "buildableType": "NONE",
        "passableMask": "FLY_ONLY",
        "playerSideMask": "ALL",
        "blackboard": null,
        "effects": null
      },
      {
        "tileKey": "tile_forbidden",
        "heightType": "HIGHLAND",
        "buildableType": "NONE",
        "passableMask": "FLY_ONLY",
        "playerSideMask": "ALL",
        "blackboard": null,
        "effects": null
      },
      {
        "tileKey": "tile_start",
        "heightType": "LOWLAND",
        "buildableType": "NONE",
        "passableMask": "ALL",
        "playerSideMask": "ALL",
        "blackboard": null,
        "effects": null
      },
      {
        "tileKey": "tile_forbidden",
        "heightType": "HIGHLAND",
        "buildableType": "NONE",
        "passableMask": "FLY_ONLY",
        "playerSideMask": "ALL",
        "blackboard": null,
        "effects": null
      },
      {
        "tileKey": "tile_forbidden",
        "heightType": "HIGHLAND",
        "buildableType": "NONE",
        "passableMask": "FLY_ONLY",
        "playerSideMask": "ALL",
        "blackboard": null,
        "effects": null
      }
    ],
    "blockEdges": null,
    "tags": [
      "rogue_yan"
    ],
    "effects": null,
    "layerRects": null
  },
  "tilesDisallowToLocate": [],
  "runes": null,
  "optionalRunes": null,
  "globalBuffs": [
    {
      "prefabKey": "rogue_5_heaven_inherit_unit_status",
      "blackboard": null,
      "overrideCameraEffect": null,
      "passProfessionMaskFlag": false,
      "professionMask": "NONE",
      "playerSideMask": "ALL"
    }
  ],
  "routes": [
    {
      "motionMode": "WALK",
      "startPosition": {
        "row": 5,
        "col": 7
      },
      "endPosition": {
        "row": 6,
        "col": 6
      },
      "spawnRandomRange": {
        "x": 0.0,
        "y": 0.0
      },
      "spawnOffset": {
        "x": 0.0,
        "y": 0.0
      },
      "checkpoints": [
        {
          "type": "WAIT_FOR_SECONDS",
          "time": 35.0,
          "position": {
            "row": 0,
            "col": 0
          },
          "reachOffset": {
            "x": 0.0,
            "y": 0.0
          },
          "randomizeReachOffset": false,
          "reachDistance": 0.0
        },
        {
          "type": "MOVE",
          "time": 0.0,
          "position": {
            "row": 2,
            "col": 7
          },
          "reachOffset": {
            "x": 0.14,
            "y": -0.09
          },
          "randomizeReachOffset": false,
          "reachDistance": 0.0
        },
        {
          "type": "WAIT_FOR_SECONDS",
          "time": 20.0,
          "position": {
            "row": 0,
            "col": 0
          },
          "reachOffset": {
            "x": 0.0,
            "y": 0.0
          },
          "randomizeReachOffset": false,
          "reachDistance": 0.0
        },
        {
          "type": "MOVE",
          "time": 0.0,
          "position": {
            "row": 5,
            "col": 5
          },
          "reachOffset": {
            "x": 0.0,
            "y": 0.0
          },
          "randomizeReachOffset": false,
          "reachDistance": 0.0
        },
        {
          "type": "WAIT_FOR_SECONDS",
          "time": 20.0,
          "position": {
            "row": 0,
            "col": 0
          },
          "reachOffset": {
            "x": 0.0,
            "y": 0.0
          },
          "randomizeReachOffset": false,
          "reachDistance": 0.0
        },
        {
          "type": "MOVE",
          "time": 0.0,
          "position": {
            "row": 5,
            "col": 7
          },
          "reachOffset": {
            "x": 0.0,
            "y": 0.0
          },
          "randomizeReachOffset": false,
          "reachDistance": 0.0
        },
        {
          "type": "WAIT_FOR_SECONDS",
          "time": 20.0,
          "position": {
            "row": 0,
            "col": 0
          },
          "reachOffset": {
            "x": 0.0,
            "y": 0.0
          },
          "randomizeReachOffset": false,
          "reachDistance": 0.0
        }
      ],
      "allowDiagonalMove": true,
      "visitEveryTileCenter": false,
      "visitEveryNodeCenter": false,
      "visitEveryCheckPoint": false
    },
    {
      "motionMode": "WALK",
      "startPosition": {
        "row": 5,
        "col": 1
      },
      "endPosition": {
        "row": 0,
        "col": 6
      },
      "spawnRandomRange": {
        "x": 0.0,
        "y": 0.0
      },
      "spawnOffset": {
        "x": 0.0,
        "y": 0.0
      },
      "checkpoints": [
        {
          "type": "WAIT_FOR_SECONDS",
          "time": 60.0,
          "position": {
            "row": 0,
            "col": 0
          },
          "reachOffset": {
            "x": 0.0,
            "y": 0.0
          },
          "randomizeReachOffset": false,
          "reachDistance": 0.0
        },
        {
          "type": "MOVE",
          "time": 0.0,
          "position": {
            "row": 5,
            "col": 0
          },
          "reachOffset": {
            "x": 0.0,
            "y": 0.0
          },
          "randomizeReachOffset": false,
          "reachDistance": 0.0
        },
        {
          "type": "DISAPPEAR",
          "time": 0.0,
          "position": {
            "row": 0,
            "col": 0
          },
          "reachOffset": {
            "x": 0.0,
            "y": 0.0
          },
          "randomizeReachOffset": false,
          "reachDistance": 0.0
        },
        {
          "type": "WAIT_FOR_SECONDS",
          "time": 5.0,
          "position": {
            "row": 0,
            "col": 0
          },
          "reachOffset": {
            "x": 0.0,
            "y": 0.0
          },
          "randomizeReachOffset": false,
          "reachDistance": 0.0
        },
        {
          "type": "APPEAR_AT_POS",
          "time": 0.0,
          "position": {
            "row": 5,
            "col": 8
          },
          "reachOffset": {
            "x": 0.0,
            "y": 0.0
          },
          "randomizeReachOffset": false,
          "reachDistance": 0.0
        },
        {
          "type": "MOVE",
          "time": 0.0,
          "position": {
            "row": 5,
            "col": 6
          },
          "reachOffset": {
            "x": 0.0,
            "y": 0.0
          },
          "randomizeReachOffset": false,
          "reachDistance": 0.0
        },
        {
          "type": "MOVE",
          "time": 0.0,
          "position": {
            "row": 2,
            "col": 6
          },
          "reachOffset": {
            "x": 0.0,
            "y": 0.0
          },
          "randomizeReachOffset": false,
          "reachDistance": 0.0
        },
        {
          "type": "MOVE",
          "time": 0.0,
          "position": {
            "row": 2,
            "col": 5
          },
          "reachOffset": {
            "x": 0.0,
            "y": 0.0
          },
          "randomizeReachOffset": false,
          "reachDistance": 0.0
        },
        {
          "type": "MOVE",
          "time": 0.0,
          "position": {
            "row": 3,
            "col": 5
          },
          "reachOffset": {
            "x": 0.0,
            "y": 0.0
          },
          "randomizeReachOffset": false,
          "reachDistance": 0.0
        },
        {
          "type": "MOVE",
          "time": 0.0,
          "position": {
            "row": 3,
            "col": 7
          },
          "reachOffset": {
            "x": 0.0,
            "y": 0.0
          },
          "randomizeReachOffset": false,
          "reachDistance": 0.0
        },
        {
          "type": "MOVE",
          "time": 0.0,
          "position": {
            "row": 2,
            "col": 7
          },
          "reachOffset": {
            "x": 0.0,
            "y": 0.0
          },
          "randomizeReachOffset": false,
          "reachDistance": 0.0
        },
        {
          "type": "MOVE",
          "time": 0.0,
          "position": {
            "row": 2,
            "col": 6
          },
          "reachOffset": {
            "x": 0.0,
            "y": 0.0
          },
          "randomizeReachOffset": false,
          "reachDistance": 0.0
        }
      ],
      "allowDiagonalMove": true,
      "visitEveryTileCenter": false,
      "visitEveryNodeCenter": false,
      "visitEveryCheckPoint": false
    },
    {
      "motionMode": "WALK",
      "startPosition": {
        "row": 1,
        "col": 2
      },
      "endPosition": {
        "row": 0,
        "col": 6
      },
      "spawnRandomRange": {
        "x": 0.0,
        "y": 0.0
      },
      "spawnOffset": {
        "x": 0.0,
        "y": 0.0
      },
      "checkpoints": [
        {
          "type": "MOVE",
          "time": 0.0,
          "position": {
            "row": 1,
            "col": 3
          },
          "reachOffset": {
            "x": 0.0,
            "y": 0.0
          },
          "randomizeReachOffset": false,
          "reachDistance": 0.0
        },
        {
          "type": "DISAPPEAR",
          "time": 0.0,
          "position": {
            "row": 0,
            "col": 0
          },
          "reachOffset": {
            "x": 0.0,
            "y": 0.0
          },
          "randomizeReachOffset": false,
          "reachDistance": 0.0
        },
        {
          "type": "WAIT_FOR_SECONDS",
          "time": 5.0,
          "position": {
            "row": 0,
            "col": 0
          },
          "reachOffset": {
            "x": 0.0,
            "y": 0.0
          },
          "randomizeReachOffset": false,
          "reachDistance": 0.0
        },
        {
          "type": "APPEAR_AT_POS",
          "time": 0.0,
          "position": {
            "row": 3,
            "col": 4
          },
          "reachOffset": {
            "x": 0.0,
            "y": 0.0
          },
          "randomizeReachOffset": false,
          "reachDistance": 0.0
        },
        {
          "type": "WAIT_FOR_SECONDS",
          "time": 50.0,
          "position": {
            "row": 0,
            "col": 0
          },
          "reachOffset": {
            "x": 0.0,
            "y": 0.0
          },
          "randomizeReachOffset": false,
          "reachDistance": 0.0
        },
        {
          "type": "MOVE",
          "time": 0.0,
          "position": {
            "row": 3,
            "col": 6
          },
          "reachOffset": {
            "x": 0.0,
            "y": 0.0
          },
          "randomizeReachOffset": false,
          "reachDistance": 0.0
        }
      ],
      "allowDiagonalMove": true,
      "visitEveryTileCenter": false,
      "visitEveryNodeCenter": false,
      "visitEveryCheckPoint": false
    },
    {
      "motionMode": "WALK",
      "startPosition": {
        "row": 5,
        "col": 6
      },
      "endPosition": {
        "row": 0,
        "col": 6
      },
      "spawnRandomRange": {
        "x": 0.0,
        "y": 0.0
      },
      "spawnOffset": {
        "x": 0.0,
        "y": 0.0
      },
      "checkpoints": [
        {
          "type": "MOVE",
          "time": 0.0,
          "position": {
            "row": 5,
            "col": 6
          },
          "reachOffset": {
            "x": 0.0,
            "y": 0.0
          },
          "randomizeReachOffset": false,
          "reachDistance": 0.0
        },
        {
          "type": "WAIT_FOR_SECONDS",
          "time": 5.0,
          "position": {
            "row": 0,
            "col": 0
          },
          "reachOffset": {
            "x": 0.0,
            "y": 0.0
          },
          "randomizeReachOffset": false,
          "reachDistance": 0.0
        }
      ],
      "allowDiagonalMove": true,
      "visitEveryTileCenter": false,
      "visitEveryNodeCenter": false,
      "visitEveryCheckPoint": false
    },
    {
      "motionMode": "FLY",
      "startPosition": {
        "row": 3,
        "col": 8
      },
      "endPosition": {
        "row": 0,
        "col": 6
      },
      "spawnRandomRange": {
        "x": 0.0,
        "y": 0.0
      },
      "spawnOffset": {
        "x": 0.0,
        "y": 0.0
      },
      "checkpoints": [
        {
          "type": "MOVE",
          "time": 0.0,
          "position": {
            "row": 3,
            "col": 6
          },
          "reachOffset": {
            "x": 0.0,
            "y": 0.0
          },
          "randomizeReachOffset": false,
          "reachDistance": 0.0
        },
        {
          "type": "WAIT_FOR_SECONDS",
          "time": 80.0,
          "position": {
            "row": 0,
            "col": 0
          },
          "reachOffset": {
            "x": 0.0,
            "y": 0.0
          },
          "randomizeReachOffset": false,
          "reachDistance": 0.0
        }
      ],
      "allowDiagonalMove": true,
      "visitEveryTileCenter": false,
      "visitEveryNodeCenter": false,
      "visitEveryCheckPoint": false
    },
    {
      "motionMode": "FLY",
      "startPosition": {
        "row": 4,
        "col": 6
      },
      "endPosition": {
        "row": 0,
        "col": 6
      },
      "spawnRandomRange": {
        "x": 0.0,
        "y": 0.0
      },
      "spawnOffset": {
        "x": 0.0,
        "y": 0.0
      },
      "checkpoints": [
        {
          "type": "WAIT_FOR_SECONDS",
          "time": 999.0,
          "position": {
            "row": 0,
            "col": 0
          },
          "reachOffset": {
            "x": 0.0,
            "y": 0.0
          },
          "randomizeReachOffset": false,
          "reachDistance": 0.0
        }
      ],
      "allowDiagonalMove": true,
      "visitEveryTileCenter": false,
      "visitEveryNodeCenter": false,
      "visitEveryCheckPoint": false
    },
    {
      "motionMode": "WALK",
      "startPosition": {
        "row": 6,
        "col": 6
      },
      "endPosition": {
        "row": 0,
        "col": 6
      },
      "spawnRandomRange": {
        "x": 0.0,
        "y": 0.0
      },
      "spawnOffset": {
        "x": 0.0,
        "y": 0.0
      },
      "checkpoints": [],
      "allowDiagonalMove": true,
      "visitEveryTileCenter": false,
      "visitEveryNodeCenter": false,
      "visitEveryCheckPoint": false
    },
    {
      "motionMode": "WALK",
      "startPosition": {
        "row": 6,
        "col": 6
      },
      "endPosition": {
        "row": 0,
        "col": 6
      },
      "spawnRandomRange": {
        "x": 0.0,
        "y": 0.0
      },
      "spawnOffset": {
        "x": 0.0,
        "y": 0.0
      },
      "checkpoints": [],
      "allowDiagonalMove": true,
      "visitEveryTileCenter": false,
      "visitEveryNodeCenter": false,
      "visitEveryCheckPoint": false
    },
    {
      "motionMode": "WALK",
      "startPosition": {
        "row": 6,
        "col": 6
      },
      "endPosition": {
        "row": 0,
        "col": 6
      },
      "spawnRandomRange": {
        "x": 0.0,
        "y": 0.0
      },
      "spawnOffset": {
        "x": 0.0,
        "y": 0.0
      },
      "checkpoints": [],
      "allowDiagonalMove": true,
      "visitEveryTileCenter": false,
      "visitEveryNodeCenter": false,
      "visitEveryCheckPoint": false
    }
  ],
  "extraRoutes": [],
  "enemies": [],
  "enemyDbRefs": [
    {
      "useDb": true,
      "id": "enemy_2001_duckmi",
      "level": 2,
      "overwrittenData": {
        "name": {
          "m_defined": false,
          "m_value": null
        },
        "description": {
          "m_defined": false,
          "m_value": null
        },
        "prefabKey": {
          "m_defined": false,
          "m_value": null
        },
        "attributes": {
          "maxHp": {
            "m_defined": false,
            "m_value": 0
          },
          "atk": {
            "m_defined": false,
            "m_value": 0
          },
          "def": {
            "m_defined": false,
            "m_value": 0
          },
          "magicResistance": {
            "m_defined": false,
            "m_value": 0.0
          },
          "cost": {
            "m_defined": false,
            "m_value": 0
          },
          "blockCnt": {
            "m_defined": false,
            "m_value": 0
          },
          "moveSpeed": {
            "m_defined": false,
            "m_value": 0.0
          },
          "attackSpeed": {
            "m_defined": false,
            "m_value": 0.0
          },
          "baseAttackTime": {
            "m_defined": false,
            "m_value": 0.0
          },
          "respawnTime": {
            "m_defined": false,
            "m_value": 0
          },
          "hpRecoveryPerSec": {
            "m_defined": false,
            "m_value": 0.0
          },
          "spRecoveryPerSec": {
            "m_defined": false,
            "m_value": 0.0
          },
          "maxDeployCount": {
            "m_defined": false,
            "m_value": 0
          },
          "massLevel": {
            "m_defined": false,
            "m_value": 0
          },
          "baseForceLevel": {
            "m_defined": false,
            "m_value": 0
          },
          "tauntLevel": {
            "m_defined": false,
            "m_value": 0
          },
          "epDamageResistance": {
            "m_defined": false,
            "m_value": 0.0
          },
          "epResistance": {
            "m_defined": false,
            "m_value": 0.0
          },
          "damageHitratePhysical": {
            "m_defined": false,
            "m_value": 0.0
          },
          "damageHitrateMagical": {
            "m_defined": false,
            "m_value": 0.0
          },
          "epBreakRecoverSpeed": {
            "m_defined": false,
            "m_value": 0.0
          },
          "stunImmune": {
            "m_defined": false,
            "m_value": false
          },
          "silenceImmune": {
            "m_defined": false,
            "m_value": false
          },
          "sleepImmune": {
            "m_defined": false,
            "m_value": false
          },
          "frozenImmune": {
            "m_defined": false,
            "m_value": false
          },
          "levitateImmune": {
            "m_defined": false,
            "m_value": false
          },
          "disarmedCombatImmune": {
            "m_defined": false,
            "m_value": false
          },
          "fearedImmune": {
            "m_defined": false,
            "m_value": false
          },
          "palsyImmune": {
            "m_defined": false,
            "m_value": false
          },
          "attractImmune": {
            "m_defined": false,
            "m_value": false
          }
        },
        "applyWay": {
          "m_defined": false,
          "m_value": "NONE"
        },
        "motion": {
          "m_defined": false,
          "m_value": "WALK"
        },
        "enemyTags": {
          "m_defined": false,
          "m_value": null
        },
        "lifePointReduce": {
          "m_defined": false,
          "m_value": 0
        },
        "levelType": {
          "m_defined": false,
          "m_value": "NORMAL"
        },
        "rangeRadius": {
          "m_defined": false,
          "m_value": 0.0
        },
        "numOfExtraDrops": {
          "m_defined": false,
          "m_value": 0
        },
        "viewRadius": {
          "m_defined": false,
          "m_value": 0.0
        },
        "notCountInTotal": {
          "m_defined": true,
          "m_value": true
        },
        "talentBlackboard": null,
        "skills": null,
        "spData": null
      }
    },
    {
      "useDb": true,
      "id": "enemy_2085_skzjxd",
      "level": 2,
      "overwrittenData": {
        "name": {
          "m_defined": false,
          "m_value": null
        },
        "description": {
          "m_defined": false,
          "m_value": null
        },
        "prefabKey": {
          "m_defined": false,
          "m_value": null
        },
        "attributes": {
          "maxHp": {
            "m_defined": false,
            "m_value": 0
          },
          "atk": {
            "m_defined": false,
            "m_value": 0
          },
          "def": {
            "m_defined": false,
            "m_value": 0
          },
          "magicResistance": {
            "m_defined": false,
            "m_value": 0.0
          },
          "cost": {
            "m_defined": false,
            "m_value": 0
          },
          "blockCnt": {
            "m_defined": false,
            "m_value": 0
          },
          "moveSpeed": {
            "m_defined": false,
            "m_value": 0.0
          },
          "attackSpeed": {
            "m_defined": false,
            "m_value": 0.0
          },
          "baseAttackTime": {
            "m_defined": false,
            "m_value": 0.0
          },
          "respawnTime": {
            "m_defined": false,
            "m_value": 0
          },
          "hpRecoveryPerSec": {
            "m_defined": false,
            "m_value": 0.0
          },
          "spRecoveryPerSec": {
            "m_defined": false,
            "m_value": 0.0
          },
          "maxDeployCount": {
            "m_defined": false,
            "m_value": 0
          },
          "massLevel": {
            "m_defined": false,
            "m_value": 0
          },
          "baseForceLevel": {
            "m_defined": false,
            "m_value": 0
          },
          "tauntLevel": {
            "m_defined": false,
            "m_value": 0
          },
          "epDamageResistance": {
            "m_defined": false,
            "m_value": 0.0
          },
          "epResistance": {
            "m_defined": false,
            "m_value": 0.0
          },
          "damageHitratePhysical": {
            "m_defined": false,
            "m_value": 0.0
          },
          "damageHitrateMagical": {
            "m_defined": false,
            "m_value": 0.0
          },
          "epBreakRecoverSpeed": {
            "m_defined": false,
            "m_value": 0.0
          },
          "stunImmune": {
            "m_defined": false,
            "m_value": false
          },
          "silenceImmune": {
            "m_defined": false,
            "m_value": false
          },
          "sleepImmune": {
            "m_defined": false,
            "m_value": false
          },
          "frozenImmune": {
            "m_defined": false,
            "m_value": false
          },
          "levitateImmune": {
            "m_defined": false,
            "m_value": false
          },
          "disarmedCombatImmune": {
            "m_defined": false,
            "m_value": false
          },
          "fearedImmune": {
            "m_defined": false,
            "m_value": false
          },
          "palsyImmune": {
            "m_defined": false,
            "m_value": false
          },
          "attractImmune": {
            "m_defined": false,
            "m_value": false
          }
        },
        "applyWay": {
          "m_defined": false,
          "m_value": "NONE"
        },
        "motion": {
          "m_defined": false,
          "m_value": "WALK"
        },
        "enemyTags": {
          "m_defined": false,
          "m_value": null
        },
        "lifePointReduce": {
          "m_defined": false,
          "m_value": 0
        },
        "levelType": {
          "m_defined": false,
          "m_value": "NORMAL"
        },
        "rangeRadius": {
          "m_defined": false,
          "m_value": 0.0
        },
        "numOfExtraDrops": {
          "m_defined": false,
          "m_value": 0
        },
        "viewRadius": {
          "m_defined": false,
          "m_value": 0.0
        },
        "notCountInTotal": {
          "m_defined": true,
          "m_value": true
        },
        "talentBlackboard": null,
        "skills": null,
        "spData": null
      }
    },
    {
      "useDb": true,
      "id": "enemy_2002_bearmi",
      "level": 2,
      "overwrittenData": {
        "name": {
          "m_defined": false,
          "m_value": null
        },
        "description": {
          "m_defined": false,
          "m_value": null
        },
        "prefabKey": {
          "m_defined": false,
          "m_value": null
        },
        "attributes": {
          "maxHp": {
            "m_defined": false,
            "m_value": 0
          },
          "atk": {
            "m_defined": false,
            "m_value": 0
          },
          "def": {
            "m_defined": false,
            "m_value": 0
          },
          "magicResistance": {
            "m_defined": false,
            "m_value": 0.0
          },
          "cost": {
            "m_defined": false,
            "m_value": 0
          },
          "blockCnt": {
            "m_defined": false,
            "m_value": 0
          },
          "moveSpeed": {
            "m_defined": false,
            "m_value": 0.0
          },
          "attackSpeed": {
            "m_defined": false,
            "m_value": 0.0
          },
          "baseAttackTime": {
            "m_defined": false,
            "m_value": 0.0
          },
          "respawnTime": {
            "m_defined": false,
            "m_value": 0
          },
          "hpRecoveryPerSec": {
            "m_defined": false,
            "m_value": 0.0
          },
          "spRecoveryPerSec": {
            "m_defined": false,
            "m_value": 0.0
          },
          "maxDeployCount": {
            "m_defined": false,
            "m_value": 0
          },
          "massLevel": {
            "m_defined": false,
            "m_value": 0
          },
          "baseForceLevel": {
            "m_defined": false,
            "m_value": 0
          },
          "tauntLevel": {
            "m_defined": false,
            "m_value": 0
          },
          "epDamageResistance": {
            "m_defined": false,
            "m_value": 0.0
          },
          "epResistance": {
            "m_defined": false,
            "m_value": 0.0
          },
          "damageHitratePhysical": {
            "m_defined": false,
            "m_value": 0.0
          },
          "damageHitrateMagical": {
            "m_defined": false,
            "m_value": 0.0
          },
          "epBreakRecoverSpeed": {
            "m_defined": false,
            "m_value": 0.0
          },
          "stunImmune": {
            "m_defined": false,
            "m_value": false
          },
          "silenceImmune": {
            "m_defined": false,
            "m_value": false
          },
          "sleepImmune": {
            "m_defined": false,
            "m_value": false
          },
          "frozenImmune": {
            "m_defined": false,
            "m_value": false
          },
          "levitateImmune": {
            "m_defined": false,
            "m_value": false
          },
          "disarmedCombatImmune": {
            "m_defined": false,
            "m_value": false
          },
          "fearedImmune": {
            "m_defined": false,
            "m_value": false
          },
          "palsyImmune": {
            "m_defined": false,
            "m_value": false
          },
          "attractImmune": {
            "m_defined": false,
            "m_value": false
          }
        },
        "applyWay": {
          "m_defined": false,
          "m_value": "NONE"
        },
        "motion": {
          "m_defined": false,
          "m_value": "WALK"
        },
        "enemyTags": {
          "m_defined": false,
          "m_value": null
        },
        "lifePointReduce": {
          "m_defined": false,
          "m_value": 0
        },
        "levelType": {
          "m_defined": false,
          "m_value": "NORMAL"
        },
        "rangeRadius": {
          "m_defined": false,
          "m_value": 0.0
        },
        "numOfExtraDrops": {
          "m_defined": false,
          "m_value": 0
        },
        "viewRadius": {
          "m_defined": false,
          "m_value": 0.0
        },
        "notCountInTotal": {
          "m_defined": true,
          "m_value": true
        },
        "talentBlackboard": null,
        "skills": null,
        "spData": null
      }
    },
    {
      "useDb": true,
      "id": "enemy_2034_sythef",
      "level": 2,
      "overwrittenData": {
        "name": {
          "m_defined": false,
          "m_value": null
        },
        "description": {
          "m_defined": false,
          "m_value": null
        },
        "prefabKey": {
          "m_defined": false,
          "m_value": null
        },
        "attributes": {
          "maxHp": {
            "m_defined": false,
            "m_value": 0
          },
          "atk": {
            "m_defined": false,
            "m_value": 0
          },
          "def": {
            "m_defined": false,
            "m_value": 0
          },
          "magicResistance": {
            "m_defined": false,
            "m_value": 0.0
          },
          "cost": {
            "m_defined": false,
            "m_value": 0
          },
          "blockCnt": {
            "m_defined": false,
            "m_value": 0
          },
          "moveSpeed": {
            "m_defined": false,
            "m_value": 0.0
          },
          "attackSpeed": {
            "m_defined": false,
            "m_value": 0.0
          },
          "baseAttackTime": {
            "m_defined": false,
            "m_value": 0.0
          },
          "respawnTime": {
            "m_defined": false,
            "m_value": 0
          },
          "hpRecoveryPerSec": {
            "m_defined": false,
            "m_value": 0.0
          },
          "spRecoveryPerSec": {
            "m_defined": false,
            "m_value": 0.0
          },
          "maxDeployCount": {
            "m_defined": false,
            "m_value": 0
          },
          "massLevel": {
            "m_defined": false,
            "m_value": 0
          },
          "baseForceLevel": {
            "m_defined": false,
            "m_value": 0
          },
          "tauntLevel": {
            "m_defined": false,
            "m_value": 0
          },
          "epDamageResistance": {
            "m_defined": false,
            "m_value": 0.0
          },
          "epResistance": {
            "m_defined": false,
            "m_value": 0.0
          },
          "damageHitratePhysical": {
            "m_defined": false,
            "m_value": 0.0
          },
          "damageHitrateMagical": {
            "m_defined": false,
            "m_value": 0.0
          },
          "epBreakRecoverSpeed": {
            "m_defined": false,
            "m_value": 0.0
          },
          "stunImmune": {
            "m_defined": false,
            "m_value": false
          },
          "silenceImmune": {
            "m_defined": false,
            "m_value": false
          },
          "sleepImmune": {
            "m_defined": false,
            "m_value": false
          },
          "frozenImmune": {
            "m_defined": false,
            "m_value": false
          },
          "levitateImmune": {
            "m_defined": false,
            "m_value": false
          },
          "disarmedCombatImmune": {
            "m_defined": false,
            "m_value": false
          },
          "fearedImmune": {
            "m_defined": false,
            "m_value": false
          },
          "palsyImmune": {
            "m_defined": false,
            "m_value": false
          },
          "attractImmune": {
            "m_defined": false,
            "m_value": false
          }
        },
        "applyWay": {
          "m_defined": false,
          "m_value": "NONE"
        },
        "motion": {
          "m_defined": false,
          "m_value": "WALK"
        },
        "enemyTags": {
          "m_defined": false,
          "m_value": null
        },
        "lifePointReduce": {
          "m_defined": false,
          "m_value": 0
        },
        "levelType": {
          "m_defined": false,
          "m_value": "NORMAL"
        },
        "rangeRadius": {
          "m_defined": false,
          "m_value": 0.0
        },
        "numOfExtraDrops": {
          "m_defined": false,
          "m_value": 0
        },
        "viewRadius": {
          "m_defined": false,
          "m_value": 0.0
        },
        "notCountInTotal": {
          "m_defined": true,
          "m_value": true
        },
        "talentBlackboard": null,
        "skills": null,
        "spData": null
      }
    },
    {
      "useDb": true,
      "id": "enemy_1042_frostd",
      "level": 0,
      "overwrittenData": null
    },
    {
      "useDb": true,
      "id": "enemy_2101_dyspll",
      "level": 0,
      "overwrittenData": null
    },
    {
      "useDb": true,
      "id": "enemy_2121_dyspl2",
      "level": 0,
      "overwrittenData": null
    },
    {
      "useDb": true,
      "id": "enemy_2119_dyshhj_2",
      "level": 0,
      "overwrittenData": null
    },
    {
      "useDb": true,
      "id": "enemy_2115_dylbg2",
      "level": 0,
      "overwrittenData": {
        "name": {
          "m_defined": false,
          "m_value": null
        },
        "description": {
          "m_defined": false,
          "m_value": null
        },
        "prefabKey": {
          "m_defined": false,
          "m_value": null
        },
        "attributes": {
          "maxHp": {
            "m_defined": false,
            "m_value": 0
          },
          "atk": {
            "m_defined": false,
            "m_value": 0
          },
          "def": {
            "m_defined": false,
            "m_value": 0
          },
          "magicResistance": {
            "m_defined": false,
            "m_value": 0.0
          },
          "cost": {
            "m_defined": false,
            "m_value": 0
          },
          "blockCnt": {
            "m_defined": false,
            "m_value": 0
          },
          "moveSpeed": {
            "m_defined": false,
            "m_value": 0.0
          },
          "attackSpeed": {
            "m_defined": false,
            "m_value": 0.0
          },
          "baseAttackTime": {
            "m_defined": false,
            "m_value": 0.0
          },
          "respawnTime": {
            "m_defined": false,
            "m_value": 0
          },
          "hpRecoveryPerSec": {
            "m_defined": false,
            "m_value": 0.0
          },
          "spRecoveryPerSec": {
            "m_defined": false,
            "m_value": 0.0
          },
          "maxDeployCount": {
            "m_defined": false,
            "m_value": 0
          },
          "massLevel": {
            "m_defined": false,
            "m_value": 0
          },
          "baseForceLevel": {
            "m_defined": false,
            "m_value": 0
          },
          "tauntLevel": {
            "m_defined": false,
            "m_value": 0
          },
          "epDamageResistance": {
            "m_defined": false,
            "m_value": 0.0
          },
          "epResistance": {
            "m_defined": false,
            "m_value": 0.0
          },
          "damageHitratePhysical": {
            "m_defined": false,
            "m_value": 0.0
          },
          "damageHitrateMagical": {
            "m_defined": false,
            "m_value": 0.0
          },
          "epBreakRecoverSpeed": {
            "m_defined": false,
            "m_value": 0.0
          },
          "stunImmune": {
            "m_defined": false,
            "m_value": false
          },
          "silenceImmune": {
            "m_defined": false,
            "m_value": false
          },
          "sleepImmune": {
            "m_defined": false,
            "m_value": false
          },
          "frozenImmune": {
            "m_defined": false,
            "m_value": false
          },
          "levitateImmune": {
            "m_defined": false,
            "m_value": false
          },
          "disarmedCombatImmune": {
            "m_defined": false,
            "m_value": false
          },
          "fearedImmune": {
            "m_defined": false,
            "m_value": false
          },
          "palsyImmune": {
            "m_defined": false,
            "m_value": false
          },
          "attractImmune": {
            "m_defined": false,
            "m_value": false
          }
        },
        "applyWay": {
          "m_defined": false,
          "m_value": "NONE"
        },
        "motion": {
          "m_defined": false,
          "m_value": "WALK"
        },
        "enemyTags": {
          "m_defined": false,
          "m_value": null
        },
        "lifePointReduce": {
          "m_defined": false,
          "m_value": 0
        },
        "levelType": {
          "m_defined": false,
          "m_value": "NORMAL"
        },
        "rangeRadius": {
          "m_defined": false,
          "m_value": 0.0
        },
        "numOfExtraDrops": {
          "m_defined": false,
          "m_value": 0
        },
        "viewRadius": {
          "m_defined": false,
          "m_value": 0.0
        },
        "notCountInTotal": {
          "m_defined": false,
          "m_value": false
        },
        "talentBlackboard": null,
        "skills": [
          {
            "prefabKey": "StartBattle",
            "priority": 0,
            "cooldown": 999.0,
            "initCooldown": 50.0,
            "spCost": 0,
            "blackboard": null
          },
          {
            "prefabKey": "FirstAid",
            "priority": 0,
            "cooldown": 20.0,
            "initCooldown": 20.0,
            "spCost": 0,
            "blackboard": [
              {
                "key": "heal_scale",
                "value": 1.2,
                "valueStr": null
              }
            ]
          }
        ],
        "spData": null
      }
    },
    {
      "useDb": true,
      "id": "enemy_2113_dyhlg2",
      "level": 0,
      "overwrittenData": {
        "name": {
          "m_defined": false,
          "m_value": null
        },
        "description": {
          "m_defined": false,
          "m_value": null
        },
        "prefabKey": {
          "m_defined": false,
          "m_value": null
        },
        "attributes": {
          "maxHp": {
            "m_defined": false,
            "m_value": 0
          },
          "atk": {
            "m_defined": false,
            "m_value": 0
          },
          "def": {
            "m_defined": false,
            "m_value": 0
          },
          "magicResistance": {
            "m_defined": false,
            "m_value": 0.0
          },
          "cost": {
            "m_defined": false,
            "m_value": 0
          },
          "blockCnt": {
            "m_defined": false,
            "m_value": 0
          },
          "moveSpeed": {
            "m_defined": false,
            "m_value": 0.0
          },
          "attackSpeed": {
            "m_defined": false,
            "m_value": 0.0
          },
          "baseAttackTime": {
            "m_defined": false,
            "m_value": 0.0
          },
          "respawnTime": {
            "m_defined": false,
            "m_value": 0
          },
          "hpRecoveryPerSec": {
            "m_defined": false,
            "m_value": 0.0
          },
          "spRecoveryPerSec": {
            "m_defined": false,
            "m_value": 0.0
          },
          "maxDeployCount": {
            "m_defined": false,
            "m_value": 0
          },
          "massLevel": {
            "m_defined": false,
            "m_value": 0
          },
          "baseForceLevel": {
            "m_defined": false,
            "m_value": 0
          },
          "tauntLevel": {
            "m_defined": false,
            "m_value": 0
          },
          "epDamageResistance": {
            "m_defined": false,
            "m_value": 0.0
          },
          "epResistance": {
            "m_defined": false,
            "m_value": 0.0
          },
          "damageHitratePhysical": {
            "m_defined": false,
            "m_value": 0.0
          },
          "damageHitrateMagical": {
            "m_defined": false,
            "m_value": 0.0
          },
          "epBreakRecoverSpeed": {
            "m_defined": false,
            "m_value": 0.0
          },
          "stunImmune": {
            "m_defined": false,
            "m_value": false
          },
          "silenceImmune": {
            "m_defined": false,
            "m_value": false
          },
          "sleepImmune": {
            "m_defined": false,
            "m_value": false
          },
          "frozenImmune": {
            "m_defined": false,
            "m_value": false
          },
          "levitateImmune": {
            "m_defined": false,
            "m_value": false
          },
          "disarmedCombatImmune": {
            "m_defined": false,
            "m_value": false
          },
          "fearedImmune": {
            "m_defined": false,
            "m_value": false
          },
          "palsyImmune": {
            "m_defined": false,
            "m_value": false
          },
          "attractImmune": {
            "m_defined": false,
            "m_value": false
          }
        },
        "applyWay": {
          "m_defined": false,
          "m_value": "NONE"
        },
        "motion": {
          "m_defined": false,
          "m_value": "WALK"
        },
        "enemyTags": {
          "m_defined": false,
          "m_value": null
        },
        "lifePointReduce": {
          "m_defined": false,
          "m_value": 0
        },
        "levelType": {
          "m_defined": false,
          "m_value": "NORMAL"
        },
        "rangeRadius": {
          "m_defined": false,
          "m_value": 0.0
        },
        "numOfExtraDrops": {
          "m_defined": false,
          "m_value": 0
        },
        "viewRadius": {
          "m_defined": false,
          "m_value": 0.0
        },
        "notCountInTotal": {
          "m_defined": false,
          "m_value": false
        },
        "talentBlackboard": null,
        "skills": [
          {
            "prefabKey": "StartBattle",
            "priority": 0,
            "cooldown": 999.0,
            "initCooldown": 60.0,
            "spCost": 0,
            "blackboard": null
          },
          {
            "prefabKey": "WindMove",
            "priority": 0,
            "cooldown": 20.0,
            "initCooldown": 0.0,
            "spCost": 0,
            "blackboard": [
              {
                "key": "duration",
                "value": 2.0,
                "valueStr": null
              },
              {
                "key": "lb_duration",
                "value": 4.0,
                "valueStr": null
              },
              {
                "key": "move_speed",
                "value": 2.0,
                "valueStr": null
              }
            ]
          },
          {
            "prefabKey": "WindEnd",
            "priority": 0,
            "cooldown": 9999.0,
            "initCooldown": 9999.0,
            "spCost": 0,
            "blackboard": []
          }
        ],
        "spData": null
      }
    },
    {
      "useDb": true,
      "id": "enemy_2111_dyyrz2",
      "level": 0,
      "overwrittenData": null
    }
  ],
  "waves": [
    {
      "preDelay": 0.0,
      "postDelay": 0.0,
      "maxTimeWaitingForNextWave": -1.0,
      "fragments": [
        {
          "preDelay": 0.0,
          "actions": [
            {
              "actionType": "SPAWN",
              "managedByScheduler": true,
              "key": "enemy_2034_sythef",
              "count": 1,
              "preDelay": 0.0,
              "interval": 1.0,
              "routeIndex": 0,
              "blockFragment": false,
              "autoPreviewRoute": true,
              "autoDisplayEnemyInfo": false,
              "isUnharmfulAndAlwaysCountAsKilled": false,
              "hiddenGroup": null,
              "randomSpawnGroupKey": null,
              "randomSpawnGroupPackKey": null,
              "randomType": "ALWAYS",
              "refreshType": "ALWAYS",
              "weight": 5,
              "dontBlockWave": false,
              "forceBlockWaveInBranch": false
            },
            {
              "actionType": "SPAWN",
              "managedByScheduler": true,
              "key": "enemy_2113_dyhlg2",
              "count": 1,
              "preDelay": 0.0,
              "interval": 1.0,
              "routeIndex": 1,
              "blockFragment": false,
              "autoPreviewRoute": false,
              "autoDisplayEnemyInfo": false,
              "isUnharmfulAndAlwaysCountAsKilled": false,
              "hiddenGroup": null,
              "randomSpawnGroupKey": null,
              "randomSpawnGroupPackKey": null,
              "randomType": "ALWAYS",
              "refreshType": "ALWAYS",
              "weight": 50,
              "dontBlockWave": false,
              "forceBlockWaveInBranch": false
            },
            {
              "actionType": "SPAWN",
              "managedByScheduler": true,
              "key": "enemy_2115_dylbg2",
              "count": 1,
              "preDelay": 0.0,
              "interval": 1.0,
              "routeIndex": 2,
              "blockFragment": false,
              "autoPreviewRoute": false,
              "autoDisplayEnemyInfo": false,
              "isUnharmfulAndAlwaysCountAsKilled": false,
              "hiddenGroup": null,
              "randomSpawnGroupKey": null,
              "randomSpawnGroupPackKey": null,
              "randomType": "ALWAYS",
              "refreshType": "ALWAYS",
              "weight": 0,
              "dontBlockWave": false,
              "forceBlockWaveInBranch": false
            },
            {
              "actionType": "SPAWN",
              "managedByScheduler": true,
              "key": "enemy_2111_dyyrz2",
              "count": 1,
              "preDelay": 0.0,
              "interval": 1.0,
              "routeIndex": 3,
              "blockFragment": false,
              "autoPreviewRoute": false,
              "autoDisplayEnemyInfo": false,
              "isUnharmfulAndAlwaysCountAsKilled": false,
              "hiddenGroup": null,
              "randomSpawnGroupKey": null,
              "randomSpawnGroupPackKey": null,
              "randomType": "ALWAYS",
              "refreshType": "ALWAYS",
              "weight": 0,
              "dontBlockWave": false,
              "forceBlockWaveInBranch": false
            },
            {
              "actionType": "SPAWN",
              "managedByScheduler": true,
              "key": "enemy_1042_frostd",
              "count": 1,
              "preDelay": 100.0,
              "interval": 1.0,
              "routeIndex": 4,
              "blockFragment": false,
              "autoPreviewRoute": false,
              "autoDisplayEnemyInfo": false,
              "isUnharmfulAndAlwaysCountAsKilled": false,
              "hiddenGroup": null,
              "randomSpawnGroupKey": null,
              "randomSpawnGroupPackKey": null,
              "randomType": "ALWAYS",
              "refreshType": "ALWAYS",
              "weight": 0,
              "dontBlockWave": false,
              "forceBlockWaveInBranch": false
            },
            {
              "actionType": "SPAWN",
              "managedByScheduler": true,
              "key": "enemy_2119_dyshhj_2",
              "count": 1,
              "preDelay": 0.0,
              "interval": 1.0,
              "routeIndex": 5,
              "blockFragment": false,
              "autoPreviewRoute": false,
              "autoDisplayEnemyInfo": false,
              "isUnharmfulAndAlwaysCountAsKilled": true,
              "hiddenGroup": "copper_b",
              "randomSpawnGroupKey": null,
              "randomSpawnGroupPackKey": null,
              "randomType": "ALWAYS",
              "refreshType": "ALWAYS",
              "weight": 0,
              "dontBlockWave": true,
              "forceBlockWaveInBranch": false
            },
            {
              "actionType": "SPAWN",
              "managedByScheduler": true,
              "key": "enemy_2001_duckmi",
              "count": 1,
              "preDelay": 160.0,
              "interval": 1.0,
              "routeIndex": 6,
              "blockFragment": false,
              "autoPreviewRoute": false,
              "autoDisplayEnemyInfo": false,
              "isUnharmfulAndAlwaysCountAsKilled": false,
              "hiddenGroup": "copper_r",
              "randomSpawnGroupKey": "tel",
              "randomSpawnGroupPackKey": null,
              "randomType": "ALWAYS",
              "refreshType": "ALWAYS",
              "weight": 5,
              "dontBlockWave": false,
              "forceBlockWaveInBranch": false
            },
            {
              "actionType": "SPAWN",
              "managedByScheduler": true,
              "key": "enemy_2002_bearmi",
              "count": 1,
              "preDelay": 160.0,
              "interval": 1.0,
              "routeIndex": 7,
              "blockFragment": false,
              "autoPreviewRoute": false,
              "autoDisplayEnemyInfo": false,
              "isUnharmfulAndAlwaysCountAsKilled": false,
              "hiddenGroup": "copper_r",
              "randomSpawnGroupKey": "tel",
              "randomSpawnGroupPackKey": null,
              "randomType": "ALWAYS",
              "refreshType": "ALWAYS",
              "weight": 5,
              "dontBlockWave": false,
              "forceBlockWaveInBranch": false
            },
            {
              "actionType": "SPAWN",
              "managedByScheduler": true,
              "key": "enemy_2085_skzjxd",
              "count": 1,
              "preDelay": 160.0,
              "interval": 1.0,
              "routeIndex": 8,
              "blockFragment": false,
              "autoPreviewRoute": false,
              "autoDisplayEnemyInfo": false,
              "isUnharmfulAndAlwaysCountAsKilled": false,
              "hiddenGroup": "copper_r",
              "randomSpawnGroupKey": "tel",
              "randomSpawnGroupPackKey": null,
              "randomType": "ALWAYS",
              "refreshType": "ALWAYS",
              "weight": 5,
              "dontBlockWave": false,
              "forceBlockWaveInBranch": false
            }
          ]
        }
      ],
      "advancedWaveTag": null
    }
  ],
  "branches": null,
  "predefines": {
    "characterInsts": [],
    "tokenInsts": [
      {
        "position": {
          "row": 3,
          "col": 3
        },
        "direction": "UP",
        "hidden": false,
        "alias": "trap_014_tower#1",
        "uniEquipIds": null,
        "showSpIllust": false,
        "masterInfos": null,
        "inst": {
          "characterKey": "trap_014_tower",
          "level": 1,
          "phase": "PHASE_0",
          "favorPoint": 0,
          "potentialRank": 0
        },
        "skillIndex": 0,
        "mainSkillLvl": 2,
        "skinId": "",
        "tmplId": null,
        "overrideSkillBlackboard": null
      },
      {
        "position": {
          "row": 4,
          "col": 8
        },
        "direction": "UP",
        "hidden": false,
        "alias": "trap_037_airsup#1",
        "uniEquipIds": null,
        "showSpIllust": false,
        "masterInfos": null,
        "inst": {
          "characterKey": "trap_037_airsup",
          "level": 1,
          "phase": "PHASE_0",
          "favorPoint": 0,
          "potentialRank": 0
        },
        "skillIndex": 0,
        "mainSkillLvl": 1,
        "skinId": "",
        "tmplId": null,
        "overrideSkillBlackboard": null
      },
      {
        "position": {
          "row": 0,
          "col": 0
        },
        "direction": "UP",
        "hidden": false,
        "alias": null,
        "uniEquipIds": null,
        "showSpIllust": false,
        "masterInfos": null,
        "inst": {
          "characterKey": "trap_251_buftrp",
          "level": 1,
          "phase": "PHASE_0",
          "favorPoint": 0,
          "potentialRank": 0
        },
        "skillIndex": -1,
        "mainSkillLvl": 1,
        "skinId": "",
        "tmplId": null,
        "overrideSkillBlackboard": null
      }
    ],
    "characterCards": [],
    "tokenCards": []
  },
  "hardPredefines": {
    "characterInsts": [],
    "tokenInsts": [],
    "characterCards": [],
    "tokenCards": []
  },
  "excludeCharIdList": null,
  "randomSeed": 9571252,
  "operaConfig": null,
  "cameraPlugin": ""
}